mkdocs_output_as_input/__init__.py
mkdocs_output_as_input/cli.py
mkdocs_output_as_input/plugin.py
vexy_mkdocs_output_as_input-1.0.9.dist-info/METADATA
vexy_mkdocs_output_as_input-1.0.9.dist-info/WHEEL
vexy_mkdocs_output_as_input-1.0.9.dist-info/entry_points.txt
vexy_mkdocs_output_as_input-1.0.9.dist-info/licenses/LICENSE
vexy_mkdocs_output_as_input-1.0.9.dist-info/RECORD
