Metadata-Version: 2.4
Name: vexy-mkdocs-output-as-input
Version: 1.0.9
Summary: MkDocs plugin that captures HTML output and creates cousin Markdown files with original frontmatter
Project-URL: Homepage, https://github.com/vexyart/vexy-mkdocs-output-as-input
Project-URL: Documentation, https://github.com/vexyart/vexy-mkdocs-output-as-input
Project-URL: Repository, https://github.com/vexyart/vexy-mkdocs-output-as-input
Project-URL: Issues, https://github.com/vexyart/vexy-mkdocs-output-as-input/issues
Project-URL: Changelog, https://github.com/vexyart/vexy-mkdocs-output-as-input/blob/main/CHANGELOG.md
Author-email: Vexy Lines Team <help@vexy.art>
Maintainer-email: Vexy Lines Team <help@vexy.art>
License: MIT
License-File: LICENSE
Keywords: documentation,html,markdown,mkdocs,plugin,postprocessing
Classifier: Development Status :: 4 - Beta
Classifier: Framework :: MkDocs
Classifier: Intended Audience :: Developers
Classifier: License :: OSI Approved :: MIT License
Classifier: Operating System :: OS Independent
Classifier: Programming Language :: Python :: 3
Classifier: Programming Language :: Python :: 3.9
Classifier: Programming Language :: Python :: 3.10
Classifier: Programming Language :: Python :: 3.11
Classifier: Programming Language :: Python :: 3.12
Classifier: Topic :: Documentation
Classifier: Topic :: Software Development :: Documentation
Classifier: Topic :: Text Processing :: Markup :: HTML
Classifier: Topic :: Text Processing :: Markup :: Markdown
Requires-Python: >=3.9
Requires-Dist: beautifulsoup4>=4.12.0
Requires-Dist: mkdocs>=1.6.0
Requires-Dist: pyyaml>=6.0
Provides-Extra: dev
Requires-Dist: black>=23.7.0; extra == 'dev'
Requires-Dist: mypy>=1.5.0; extra == 'dev'
Requires-Dist: pre-commit>=3.3.0; extra == 'dev'
Requires-Dist: pytest-cov>=4.1.0; extra == 'dev'
Requires-Dist: pytest-mock>=3.11.0; extra == 'dev'
Requires-Dist: pytest>=7.4.0; extra == 'dev'
Requires-Dist: ruff>=0.1.0; extra == 'dev'
Requires-Dist: types-beautifulsoup4>=4.12.0; extra == 'dev'
Requires-Dist: types-pyyaml>=6.0.0; extra == 'dev'
Provides-Extra: docs
Requires-Dist: mkdocstrings[python]>=0.24.0; extra == 'docs'
Requires-Dist: vexy-mkdocs-material>=9.4.0; extra == 'docs'
